i_hate_papers/__init__.py
i_hate_papers/arxiv_utils.py
i_hate_papers/html_utils.py
i_hate_papers/latex_utils.py
i_hate_papers/main.py
i_hate_papers/markdown_utils.py
i_hate_papers/md_parser.py
i_hate_papers/openai_utils.py
i_hate_papers/settings.py
i_hate_papers-0.2.1.dist-info/METADATA
i_hate_papers-0.2.1.dist-info/WHEEL
i_hate_papers-0.2.1.dist-info/entry_points.txt
i_hate_papers-0.2.1.dist-info/RECORD
