Metadata-Version: 2.1
Name: i-hate-papers
Version: 0.2.1
Summary: Create easily readable versions of academic papers via OpenAI
Home-page: https://github.com/adamcharnock/i-hate-papers
License: MIT
Author: Adam Charnock
Author-email: adam@adamcharnock.com
Requires-Python: >=3.9,<4.0
Classifier: License :: OSI Approved :: MIT License
Classifier: Programming Language :: Python :: 3
Classifier: Programming Language :: Python :: 3.9
Classifier: Programming Language :: Python :: 3.10
Classifier: Programming Language :: Python :: 3.11
Classifier: Topic :: Scientific/Engineering :: Artificial Intelligence
Classifier: Topic :: Text Processing
Requires-Dist: arxiv (>=1.4.8,<2.0.0)
Requires-Dist: html2text (>=2020.1.16,<2021.0.0)
Requires-Dist: markdown (>=3.4.4,<4.0.0)
Requires-Dist: openai (>=0.27.10,<0.28.0)
Requires-Dist: python-markdown-math (>=0.8,<0.9)
